primosutilsjdm/__init__.py
primosutilsjdm-1.0.dist-info/LICENSE.txt
primosutilsjdm-1.0.dist-info/METADATA
primosutilsjdm-1.0.dist-info/WHEEL
primosutilsjdm-1.0.dist-info/top_level.txt
primosutilsjdm-1.0.dist-info/RECORD
